pypulse/__init__.py
pypulse/manage.py
pypulse/Aplication/__init__.py
pypulse/Aplication/aplication.py
pypulse/Aplication/get_aplication.py
pypulse/Aplication/reader.py
pypulse/Aplication/set_aplication.py
pypulse/Aplication/vars.py
pypulse/Socket/__init__.py
pypulse/Socket/request_handler.py
pypulse/Socket/server.py
pypulse/Template/__init__.py
pypulse/Template/render_template.py
pypulse/Template/template.py
pypulse/Utils/__init__.py
pypulse/Utils/call_ast_exec_module.py
pypulse/View/__init__.py
pypulse/View/callview.py
pypulse/View/setview.py
pypulse/View/view.py
pypulse/Window/__init__.py
pypulse/Window/browser.py
pypulse/Window/load_browser.py
pypulse/Window/set_icon_windows.py
tests/__init__.py
tests/window.py
chromium_pypulse-0.1.dist-info/LICENSE
chromium_pypulse-0.1.dist-info/METADATA
chromium_pypulse-0.1.dist-info/WHEEL
chromium_pypulse-0.1.dist-info/entry_points.txt
chromium_pypulse-0.1.dist-info/top_level.txt
chromium_pypulse-0.1.dist-info/RECORD
