Metadata-Version: 2.1
Name: chromium-pypulse
Version: 0.1
Summary: Python, create desktop applications based on Chromium
Author: zabbix-byte
License: MIT
Classifier: Development Status :: 3 - Alpha
Classifier: Intended Audience :: Developers
Classifier: Topic :: Software Development :: Build Tools
Classifier: License :: OSI Approved :: MIT License
Classifier: Programming Language :: Python :: 3.8
License-File: LICENSE
Requires-Dist: cefpython3 ==66.1
Requires-Dist: Jinja2 ==3.1.2
Requires-Dist: wxPython ==4.2.1
